rtl/expanda_rejection_sampler.v
// Original project implementation. ML-DSA-44 RejNTTPoly byte-stream sampler.
`timescale 1ns/1ps
module expanda_rejection_sampler (
    input wire clk, rst,
    input wire start,
    input wire [7:0] byte_data,
    input wire byte_valid,
    output wire byte_ready,
    output reg [22:0] coeff_data,
    output reg coeff_valid,
    input wire coeff_ready,
    output wire coeff_last,
    output reg busy, done
);
    reg [1:0] byte_index;
    reg [15:0] candidate_low;
    reg [8:0] accepted_count;
    wire [22:0] candidate = {byte_data[6:0], candidate_low};
    // One pending coefficient: stop input until it is accepted downstream.
    assign byte_ready = busy && !coeff_valid;
    assign coeff_last = coeff_valid && (accepted_count == 9'd255);
    always @(posedge clk) begin
        if (rst) begin
            byte_index <= 0; candidate_low <= 0; accepted_count <= 0;
            coeff_data <= 0; coeff_valid <= 0; busy <= 0; done <= 0;
        end else begin
            done <= 0;
            if (start && !busy) begin
                byte_index <= 0; candidate_low <= 0; accepted_count <= 0;
                coeff_valid <= 0; busy <= 1;
            end else begin
                if (byte_valid && byte_ready) begin
                    case (byte_index)
                        0: begin candidate_low[7:0] <= byte_data; byte_index <= 1; end
                        1: begin candidate_low[15:8] <= byte_data; byte_index <= 2; end
                        2: begin
                            byte_index <= 0;
                            if (candidate < 23'd8380417) begin
                                coeff_data <= candidate;
                                coeff_valid <= 1;
                            end
                        end
                        default: byte_index <= 0;
                    endcase
                end
                if (coeff_valid && coeff_ready) begin
                    coeff_valid <= 0;
                    accepted_count <= accepted_count + 1'b1;
                    if (accepted_count == 255) begin busy <= 0; done <= 1; end
                end
            end
        end
    end
endmodule

tb/tb_expanda_sampler.v
`timescale 1ns/1ps
module tb_expanda_sampler;
    reg clk=0; always #5 clk=~clk;
    reg rst=1,start=0,byte_valid=0,coeff_ready=0;
    reg [7:0] byte_data=0;
    wire byte_ready,coeff_valid,coeff_last,busy,done;
    wire [22:0] coeff;
    reg [7:0] stream [0:38399];
    reg [22:0] expected [0:8191];
    integer tick=0,cursor=0,count=0,done_count=0,stalls=0;
    reg checking=0, take_byte,take_coeff,take_done,prev_stall=0;
    reg [22:0] held_coeff;
    reg held_last;
    expanda_rejection_sampler dut (
        .clk(clk),.rst(rst),.start(start),.byte_data(byte_data),
        .byte_valid(byte_valid),.byte_ready(byte_ready),.coeff_data(coeff),
        .coeff_valid(coeff_valid),.coeff_ready(coeff_ready),.coeff_last(coeff_last),
        .busy(busy),.done(done)
    );
    always @(negedge clk) begin
        tick=tick+1;
        coeff_ready=checking && (tick%19>=9);
        if(checking && busy && !byte_valid && tick%7!=0) begin
            byte_data=stream[cursor];byte_valid=1;
        end
    end
    always @(posedge clk) begin
        take_byte=byte_valid && byte_ready;
        take_coeff=coeff_valid && coeff_ready;
        take_done=done;
        if(checking && !rst) begin
            if(prev_stall && (!coeff_valid || coeff!==held_coeff || coeff_last!==held_last))
                begin $display("FAIL: output changed while stalled"); $finish; end
            prev_stall=coeff_valid && !coeff_ready;
            if(prev_stall) begin held_coeff=coeff;held_last=coeff_last;stalls=stalls+1;end
            if(take_coeff) begin
                if(count>=256 || coeff!==expected[count]) begin $display("FAIL: sampler coefficient mismatch %0d",count); $finish; end
                if(coeff_last !== (count==255)) begin $display("FAIL: wrong coeff_last"); $finish; end
                count=count+1;
            end
            if(take_done) done_count=done_count+1;
        end
        #1;
        if(checking && take_byte) begin cursor=cursor+1;byte_valid=0;end
    end
    initial begin
        $dumpfile("results/expanda_sampler.vcd");
        $dumpvars(0,tb_expanda_sampler);
        $readmemh("vectors/expanda_bytes.hex",stream);
        $readmemh("vectors/expanda_coeffs.hex",expected);
        repeat(3) @(negedge clk);rst=0;start=1;
        @(negedge clk);start=0;byte_valid=1;byte_data=8'hfe;
        @(negedge clk);byte_valid=0;
        // Abort a partial three-byte candidate, then start a fresh polynomial.
        @(negedge clk);rst=1;
        @(negedge clk);rst=0;checking=1;start=1;
        @(negedge clk);start=0;
        wait(done);repeat(3) @(negedge clk);
        if(count!=256 || done_count!=1 || stalls==0 || busy || coeff_valid || byte_ready)
            begin $display("FAIL: bad final sampler state"); $finish; end
        $display("PASS: sampler reset, rejection boundaries, output stability through %0d stall cycles, exact 256 termination.",stalls);
        $finish;
    end
    initial begin #500000;begin $display("FAIL: sampler timeout"); $finish; end end
endmodule

results/expanda_sampler.vcd
$date
	Thu Oct 08 19:39:17 2026
$end
$version
	Icarus Verilog
$end
$timescale
	1ps
$end
$scope module tb_expanda_sampler $end
$var wire 1 ! done $end
$var wire 1 " coeff_valid $end
$var wire 1 # coeff_last $end
$var wire 23 $ coeff [22:0] $end
$var wire 1 % byte_ready $end
$var wire 1 & busy $end
$var reg 8 ' byte_data [7:0] $end
$var reg 1 ( byte_valid $end
$var reg 1 ) checking $end
$var reg 1 * clk $end
$var reg 1 + coeff_ready $end
$var reg 23 , held_coeff [22:0] $end
$var reg 1 - held_last $end
$var reg 1 . prev_stall $end
$var reg 1 / rst $end
$var reg 1 0 start $end
$var reg 1 1 take_byte $end
$var reg 1 2 take_coeff $end
$var reg 1 3 take_done $end
$var integer 32 4 count [31:0] $end
$var integer 32 5 cursor [31:0] $end
$var integer 32 6 done_count [31:0] $end
$var integer 32 7 stalls [31:0] $end
$var integer 32 8 tick [31:0] $end
$scope module dut $end
$var wire 8 9 byte_data [7:0] $end
$var wire 1 % byte_ready $end
$var wire 1 ( byte_valid $end
$var wire 1 * clk $end
$var wire 1 # coeff_last $end
$var wire 1 + coeff_ready $end
$var wire 1 / rst $end
$var wire 1 0 start $end
$var wire 23 : candidate [22:0] $end
$var reg 9 ; accepted_count [8:0] $end
$var reg 1 & busy $end
$var reg 2 < byte_index [1:0] $end
$var reg 16 = candidate_low [15:0] $end
$var reg 23 > coeff_data [22:0] $end
$var reg 1 " coeff_valid $end
$var reg 1 ! done $end
$upscope $end
$upscope $end
$enddefinitions $end
$comment Show the parameter values. $end
$dumpall
$end
#0
$dumpvars
bx >
bx =
bx <
bx ;
b0xxxxxxxxxxxxxxxx :
b0 9
b0 8
b0 7
b0 6
b0 5
b0 4
x3
x2
x1
00
1/
0.
x-
bx ,
0+
0*
0)
0(
b0 '
x&
x%
bx $
x#
x"
x!
$end
#5000
0%
0#
0!
0&
0"
b0 $
b0 >
b0 ;
b0 :
b0 =
b0 <
02
01
1*
#10000
b1 8
0*
#15000
03
1*
#20000
b10 8
0*
#25000
1*
#30000
b11 8
10
0/
0*
#35000
1%
1&
1*
#40000
b11111100000000000000000 :
b11111110 '
b11111110 9
1(
00
b100 8
0*
#45000
b1 <
b11111100000000011111110 :
b11111110 =
11
1*
#50000
b101 8
0(
0*
#55000
01
1*
#60000
1/
b110 8
0*
#65000
0%
0&
b11111100000000000000000 :
b0 =
b0 <
1*
#70000
b111 8
10
1)
0/
0*
#75000
1%
1&
1*
#80000
b10000000000000000 :
00
1(
b1 '
b1 9
b1000 8
0*
#85000
b1 <
b10000000000000001 :
b1 =
11
1*
#86000
0(
b1 5
#90000
b11000000000000000000001 :
1(
b11100000 '
b11100000 9
1+
b1001 8
0*
#95000
b10 <
b11000001110000000000001 :
b1110000000000001 =
1*
#96000
0(
b10 5
#100000
b11111111110000000000001 :
1(
b1111111 '
b1111111 9
b1010 8
0*
#105000
b0 <
1*
#106000
0(
b11 5
#110000
b101110000000000001 :
1(
b10 '
b10 9
b1011 8
0*
#115000
b1 <
b101110000000000010 :
b1110000000000010 =
1*
#116000
0(
b100 5
#120000
b11000001110000000000010 :
1(
b11100000 '
b11100000 9
b1100 8
0*
#125000
b10 <
1*
#126000
0(
b101 5
#130000
b11111111110000000000010 :
1(
b1111111 '
b1111111 9
b1101 8
0*
#135000
b0 <
1*
#136000
0(
b110 5
#140000
b1110 8
0*
#145000
01
1*
#150000
1(
b11111111 '
b11111111 9
b1111 8
0*
#155000
b1 <
b11111111110000011111111 :
b1110000011111111 =
11
1*
#156000
0(
b111 5
#160000
1(
b10000 8
0*
#165000
b10 <
b11111111111111111111111 :
b1111111111111111 =
1*
#166000
0(
b1000 5
#170000
1(
b10001 8
0*
#175000
b0 <
1*
#176000
0(
b1001 5
#180000
b1111111111111111 :
1(
b0 '
b0 9
b10010 8
0*
#185000
b1 <
b1111111100000000 :
b1111111100000000 =
1*
#186000
0(
b1010 5
#190000
1(
0+
b10011 8
0*
#195000
b10 <
b0 :
b0 =
1*
#196000
0(
b1011 5
#200000
1(
b10000000 '
b10000000 9
b10100 8
0*
#205000
0%
1"
b0 <
1*
#206000
0(
b1100 5
#210000
b10101 8
0*
#215000
b1 7
0-
b0 ,
1.
01
1*
#220000
1(
b0 '
b0 9
b10110 8
0*
#225000
b10 7
1*
#230000
b10111 8
0*
#235000
b11 7
1*
#240000
b11000 8
0*
#245000
b100 7
1*
#250000
b11001 8
0*
#255000
b101 7
1*
#260000
b11010 8
0*
#265000
b110 7
1*
#270000
b11011 8
0*
#275000
b111 7
1*
#280000
1+
b11100 8
0*
#285000
1%
b1 ;
0"
b1 4
0.
12
1*
#290000
b11101 8
0*
#295000
b1 <
02
11
1*
#296000
0(
b1101 5
#300000
b11000000000000000000000 :
1(
b11100000 '
b11100000 9
b11110 8
0*
#305000
b10 <
b11000001110000000000000 :
b1110000000000000 =
1*
#306000
0(
b1110 5
#310000
b11111111110000000000000 :
1(
b1111111 '
b1111111 9
b11111 8
0*
#315000
0%
1"
b11111111110000000000000 $
b11111111110000000000000 >
b0 <
1*
#316000
0(
b1111 5
#320000
b1110000000000000 :
1(
b0 '
b0 9
b100000 8
0*
#325000
1%
b10 ;
0"
b10 4
12
01
1*
#330000
b100001 8
0*
#335000
b1 <
02
11
1*
#336000
0(
b10000 5
#340000
1(
b100010 8
0*
#345000
b10 <
b0 :
b0 =
1*
#346000
0(
b10001 5
#350000
b100011 8
0*
#355000
01
1*
#360000
1(
b100100 8
0*
#365000
0%
1"
b0 $
b0 >
b0 <
11
1*
#366000
0(
b10010 5
#370000
b10000000000000000 :
1(
b1 '
b1 9
b100101 8
0*
#375000
1%
b11 ;
0"
b11 4
12
01
1*
#380000
0+
b100110 8
0*
#385000
b1 <
b10000000000000001 :
b1 =
02
11
1*
#386000
0(
b10011 5
#390000
b1 :
1(
b0 '
b0 9
b100111 8
0*
#395000
b10 <
1*
#396000
0(
b10100 5
#400000
1(
b10000000 '
b10000000 9
b101000 8
0*
#405000
0%
1"
b1 $
b1 >
b0 <
1*
#406000
0(
b10101 5
#410000
b100000000000000001 :
1(
b10 '
b10 9
b101001 8
0*
#415000
b1000 7
b1 ,
1.
01
1*
#420000
b101010 8
0*
#425000
b1001 7
1*
#430000
b101011 8
0*
#435000
b1010 7
1*
#440000
b101100 8
0*
#445000
b1011 7
1*
#450000
b101101 8
0*
#455000
b1100 7
1*
#460000
b101110 8
0*
#465000
b1101 7
1*
#470000
1+
b101111 8
0*
#475000
1%
b100 ;
0"
b100 4
0.
12
1*
#480000
b110000 8
0*
#485000
b1 <
b100000000000000010 :
b10 =
02
11
1*
#486000
0(
b10110 5
#490000
b110001 8
0*
#495000
01
1*
#500000
b10 :
1(
b0 '
b0 9
b110010 8
0*
#505000
b10 <
11
1*
#506000
0(
b10111 5
#510000
1(
b110011 8
0*
#515000
0%
1"
b10 $
b10 >
b0 <
1*
#516000
0(
b11000 5
#520000
b110000000000000010 :
1(
b11 '
b11 9
b110100 8
0*
#525000
1%
b101 ;
0"
b101 4
12
01
1*
#530000
b110101 8
0*
#535000
b1 <
b110000000000000011 :
b11 =
02
11
1*
#536000
0(
b11001 5
#540000
b11 :
1(
b0 '
b0 9
b110110 8
0*
#545000
b10 <
1*
#546000
0(
b11010 5
#550000
1(
b10000000 '
b10000000 9
b110111 8
0*
#555000
0%
1"
b11 $
b11 >
b0 <
1*
#556000
0(
b11011 5
#560000
b111000 8
0*
#565000
1%
b110 ;
0"
b110 4
12
01
1*
#570000
b1000000000000000011 :
1(
b100 '
b100 9
0+
b111001 8
0*
#575000
b1 <
b1000000000000000100 :
b100 =
02
11
1*
#576000
0(
b11100 5
#580000
b100 :
1(
b0 '
b0 9
b111010 8
0*
#585000
b10 <
1*
#586000
0(
b11101 5
#590000
1(
b111011 8
0*
#595000
0%
1"
b100 $
b100 >
b0 <
1*
#596000
0(
b11110 5
#600000
b1010000000000000100 :
1(
b101 '
b101 9
b111100 8
0*
#605000
b1110 7
b100 ,
1.
01
1*
#610000
b111101 8
0*
#615000
b1111 7
1*
#620000
b111110 8
0*
#625000
b10000 7
1*
#630000
b111111 8
0*
#635000
b10001 7
1*
#640000
b1000000 8
0*
#645000
b10010 7
1*
#650000
b1000001 8
0*
#655000
b10011 7
1*
#660000
1+
b1000010 8
0*
#665000
1%
b111 ;
0"
b111 4
0.
12
1*
#670000
b1000011 8
0*
#675000
b1 <
b1010000000000000101 :
b101 =
02
11
1*
#676000
0(
b11111 5
#680000
b101 :
1(
b0 '
b0 9
b1000100 8
0*
#685000
b10 <
1*
#686000
0(
b100000 5
#690000
1(
b10000000 '
b10000000 9
b1000101 8
0*
#695000
0%
1"
b101 $
b101 >
b0 <
1*
#696000
0(
b100001 5
#700000
b1000110 8
0*
#705000
1%
b1000 ;
0"
b1000 4
12
01
1*
#710000
b1100000000000000101 :
1(
b110 '
b110 9
b1000111 8
0*
#715000
b1 <
b1100000000000000110 :
b110 =
02
11
1*
#716000
0(
b100010 5
#720000
b110 :
1(
b0 '
b0 9
b1001000 8
0*
#725000
b10 <
1*
#726000
0(
b100011 5
#730000
1(
b1001001 8
0*
#735000
0%
1"
b110 $
b110 >
b0 <
1*
#736000
0(
b100100 5
#740000
b1110000000000000110 :
1(
b111 '
b111 9
b1001010 8
0*
#745000
1%
b1001 ;
0"
b1001 4
12
01
1*
#750000
b1001011 8
0*
#755000
b1 <
b1110000000000000111 :
b111 =
02
11
1*
#756000
0(
b100101 5
#760000
b111 :
1(
b0 '
b0 9
0+
b1001100 8
0*
#765000
b10 <
1*
#766000
0(
b100110 5
#770000
b1001101 8
0*
#775000
01
1*
#780000
1(
b10000000 '
b10000000 9
b1001110 8
0*
#785000
0%
1"
b111 $
b111 >
b0 <
11
1*
#786000
0(
b100111 5
#790000
b10000000000000000111 :
1(
b1000 '
b1000 9
b1001111 8
0*
#795000
b10100 7
b111 ,
1.
01
1*
#800000
b1010000 8
0*
#805000
b10101 7
1*
#810000
b1010001 8
0*
#815000
b10110 7
1*
#820000
b1010010 8
0*
#825000
b10111 7
1*
#830000
b1010011 8
0*
#835000
b11000 7
1*
#840000
b1010100 8
0*
#845000
b11001 7
1*
#850000
1+
b1010101 8
0*
#855000
1%
b1010 ;
0"
b1010 4
0.
12
1*
#860000
b1010110 8
0*
#865000
b1 <
b10000000000000001000 :
b1000 =
02
11
1*
#866000
0(
b101000 5
#870000
b1000 :
1(
b0 '
b0 9
b1010111 8
0*
#875000
b10 <
1*
#876000
0(
b101001 5
#880000
1(
b1011000 8
0*
#885000
0%
1"
b1000 $
b1000 >
b0 <
1*
#886000
0(
b101010 5
#890000
b10010000000000001000 :
1(
b1001 '
b1001 9
b1011001 8
0*
#895000
1%
b1011 ;
0"
b1011 4
12
01
1*
#900000
b1011010 8
0*
#905000
b1 <
b10010000000000001001 :
b1001 =
02
11
1*
#906000
0(
b101011 5
#910000
b1011011 8
0*
#915000
01
1*
#920000
b1001 :
1(
b0 '
b0 9
b1011100 8
0*
#925000
b10 <
11
1*
#926000
0(
b101100 5
#930000
1(
b10000000 '
b10000000 9
b1011101 8
0*
#935000
0%
1"
b1001 $
b1001 >
b0 <
1*
#936000
0(
b101101 5
#940000
b10100000000000001001 :
1(
b1010 '
b1010 9
b1011110 8
0*
#945000
1%
b1100 ;
0"
b1100 4
12
01
1*
#950000
0+
b1011111 8
0*
#955000
b1 <
b10100000000000001010 :
b1010 =
02
11
1*
#956000
0(
b101110 5
#960000
b1010 :
1(
b0 '
b0 9
b1100000 8
0*
#965000
b10 <
1*
#966000
0(
b101111 5
#970000
1(
b1100001 8
0*
#975000
0%
1"
b1010 $
b1010 >
b0 <
1*
#976000
0(
b110000 5
#980000
b1100010 8
0*
#985000
b11010 7
b1010 ,
1.
01
1*
#990000
b10110000000000001010 :
1(
b1011 '
b1011 9
b1100011 8
0*
#995000
b11011 7
1*
#1000000
b1100100 8
0*
#1005000
b11100 7
1*
#1010000
b1100101 8
0*
#1015000
b11101 7
1*
#1020000
b1100110 8
0*
#1025000
b11110 7
1*
#1030000
b1100111 8
0*
#1035000
b11111 7
1*
#1040000
1+
b1101000 8
0*
#1045000
1%
b1101 ;
0"
b1101 4
0.
12
1*
#1050000
b1101001 8
0*
#1055000
b1 <
b10110000000000001011 :
b1011 =
02
11
1*
#1056000
0(
b110001 5
#1060000
b1011 :
1(
b0 '
b0 9
b1101010 8
0*
#1065000
b10 <
1*
#1066000
0(
b110010 5
#1070000
1(
b10000000 '
b10000000 9
b1101011 8
0*
#1075000
0%
1"
b1011 $
b1011 >
b0 <
1*
#1076000
0(
b110011 5
#1080000
b11000000000000001011 :
1(
b1100 '
b1100 9
b1101100 8
0*
#1085000
1%
b1110 ;
0"
b1110 4
12
01
1*
#1090000
b1101101 8
0*
#1095000
b1 <
b11000000000000001100 :
b1100 =
02
11
1*
#1096000
0(
b110100 5
#1100000
b1100 :
1(
b0 '
b0 9
b1101110 8
0*
#1105000
b10 <
1*
#1106000
0(
b110101 5
#1110000
1(
b1101111 8
0*
#1115000
0%
1"
b1100 $
b1100 >
b0 <
1*
#1116000
0(
b110110 5
#1120000
b1110000 8
0*
#1125000
1%
b1111 ;
0"
b1111 4
12
01
1*
#1130000
b11010000000000001100 :
1(
b1101 '
b1101 9
b1110001 8
0*
#1135000
b1 <
b11010000000000001101 :
b1101 =
02
11
1*
#1136000
0(
b110111 5
#1140000
b1101 :
1(
b0 '
b0 9
0+
b1110010 8
0*
#1145000
b10 <
1*
#1146000
0(
b111000 5
#1150000
1(
b10000000 '
b10000000 9
b1110011 8
0*
#1155000
0%
1"
b1101 $
b1101 >
b0 <
1*
#1156000
0(
b111001 5
#1160000
b11100000000000001101 :
1(
b1110 '
b1110 9
b1110100 8
0*
#1165000
b100000 7
b1101 ,
1.
01
1*
#1170000
b1110101 8
0*
#1175000
b100001 7
1*
#1180000
b1110110 8
0*
#1185000
b100010 7
1*
#1190000
b1110111 8
0*
#1195000
b100011 7
1*
#1200000
b1111000 8
0*
#1205000
b100100 7
1*
#1210000
b1111001 8
0*
#1215000
b100101 7
1*
#1220000
b1111010 8
0*
#1225000
b100110 7
1*
#1230000
1+
b1111011 8
0*
#1235000
1%
b10000 ;
0"
b10000 4
0.
12
1*
#1240000
b1111100 8
0*
#1245000
b1 <
b11100000000000001110 :
b1110 =
02
11
1*
#1246000
0(
b111010 5
#1250000
b1110 :
1(
b0 '
b0 9
b1111101 8
0*
#1255000
b10 <
1*
#1256000
0(
b111011 5
#1260000
b1111110 8
0*
#1265000
01
1*
#1270000
1(
b1111111 8
0*
#1275000
0%
1"
b1110 $
b1110 >
b0 <
11
1*
#1276000
0(
b111100 5
#1280000
b11110000000000001110 :
1(
b1111 '
b1111 9
b10000000 8
0*
#1285000
1%
b10001 ;
0"
b10001 4
12
01
1*
#1290000
b10000001 8
0*
#1295000
b1 <
b11110000000000001111 :
b1111 =
02
11
1*
#1296000
0(
b111101 5
#1300000
b1111 :
1(
b0 '
b0 9
b10000010 8
0*
#1305000
b10 <
1*
#1306000
0(
b111110 5
#1310000
1(
b10000000 '
b10000000 9
b10000011 8
0*
#1315000
0%
1"
b1111 $
b1111 >
b0 <
1*
#1316000
0(
b111111 5
#1320000
b100000000000000001111 :
1(
b10000 '
b10000 9
b10000100 8
0*
#1325000
1%
b10010 ;
0"
b10010 4
12
01
1*
#1330000
0+
b10000101 8
0*
#1335000
b1 <
b100000000000000010000 :
b10000 =
02
11
1*
#1336000
0(
b1000000 5
#1340000
b10000 :
1(
b0 '
b0 9
b10000110 8
0*
#1345000
b10 <
1*
#1346000
0(
b1000001 5
#1350000
1(
b10000111 8
0*
#1355000
0%
1"
b10000 $
b10000 >
b0 <
1*
#1356000
0(
b1000010 5
#1360000
b100010000000000010000 :
1(
b10001 '
b10001 9
b10001000 8
0*
#1365000
b100111 7
b10000 ,
1.
01
1*
#1370000
b10001001 8
0*
#1375000
b101000 7
1*
#1380000
b10001010 8
0*
#1385000
b101001 7
1*
#1390000
b10001011 8
0*
#1395000
b101010 7
1*
#1400000
b10001100 8
0*
#1405000
b101011 7
1*
#1410000
b10001101 8
0*
#1415000
b101100 7
1*
#1420000
1+
b10001110 8
0*
#1425000
1%
b10011 ;
0"
b10011 4
0.
12
1*
#1430000
b10001111 8
0*
#1435000
b1 <
b100010000000000010001 :
b10001 =
02
11
1*
#1436000
0(
b1000011 5
#1440000
b10001 :
1(
b0 '
b0 9
b10010000 8
0*
#1445000
b10 <
1*
#1446000
0(
b1000100 5
#1450000
1(
b10000000 '
b10000000 9
b10010001 8
0*
#1455000
0%
1"
b10001 $
b10001 >
b0 <
1*
#1456000
0(
b1000101 5
#1460000
b100100000000000010001 :
1(
b10010 '
b10010 9
b10010010 8
0*
#1465000
1%
b10100 ;
0"
b10100 4
12
01
1*
#1470000
b10010011 8
0*
#1475000
b1 <
b100100000000000010010 :
b10010 =
02
11
1*
#1476000
0(
b1000110 5
#1480000
b10010 :
1(
b0 '
b0 9
b10010100 8
0*
#1485000
b10 <
1*
#1486000
0(
b1000111 5
#1490000
1(
b10010101 8
0*
#1495000
0%
1"
b10010 $
b10010 >
b0 <
1*
#1496000
0(
b1001000 5
#1500000
b100110000000000010010 :
1(
b10011 '
b10011 9
b10010110 8
0*
#1505000
1%
b10101 ;
0"
b10101 4
12
01
1*
#1510000
b10010111 8
0*
#1515000
b1 <
b100110000000000010011 :
b10011 =
02
11
1*
#1516000
0(
b1001001 5
#1520000
b10011 :
1(
b0 '
b0 9
0+
b10011000 8
0*
#1525000
b10 <
1*
#1526000
0(
b1001010 5
#1530000
1(
b10000000 '
b10000000 9
b10011001 8
0*
#1535000
0%
1"
b10011 $
b10011 >
b0 <
1*
#1536000
0(
b1001011 5
#1540000
b10011010 8
0*
#1545000
b101101 7
b10011 ,
1.
01
1*
#1550000
b101000000000000010011 :
1(
b10100 '
b10100 9
b10011011 8
0*
#1555000
b101110 7
1*
#1560000
b10011100 8
0*
#1565000
b101111 7
1*
#1570000
b10011101 8
0*
#1575000
b110000 7
1*
#1580000
b10011110 8
0*
#1585000
b110001 7
1*
#1590000
b10011111 8
0*
#1595000
b110010 7
1*
#1600000
b10100000 8
0*
#1605000
b110011 7
1*
#1610000
1+
b10100001 8
0*
#1615000
1%
b10110 ;
0"
b10110 4
0.
12
1*
#1620000
b10100010 8
0*
#1625000
b1 <
b101000000000000010100 :
b10100 =
02
11
1*
#1626000
0(
b1001100 5
#1630000
b10100 :
1(
b0 '
b0 9
b10100011 8
0*
#1635000
b10 <
1*
#1636000
0(
b1001101 5
#1640000
1(
b10100100 8
0*
#1645000
0%
1"
b10100 $
b10100 >
b0 <
1*
#1646000
0(
b1001110 5
#1650000
b101010000000000010100 :
1(
b10101 '
b10101 9
b10100101 8
0*
#1655000
1%
b10111 ;
0"
b10111 4
12
01
1*
#1660000
b10100110 8
0*
#1665000
b1 <
b101010000000000010101 :
b10101 =
02
11
1*
#1666000
0(
b1001111 5
#1670000
b10101 :
1(
b0 '
b0 9
b10100111 8
0*
#1675000
b10 <
1*
#1676000
0(
b1010000 5
#1680000
b10101000 8
0*
#1685000
01
1*
#1690000
1(
b10000000 '
b10000000 9
b10101001 8
0*
#1695000
0%
1"
b10101 $
b10101 >
b0 <
11
1*
#1696000
0(
b1010001 5
#1700000
b101100000000000010101 :
1(
b10110 '
b10110 9
b10101010 8
0*
#1705000
1%
b11000 ;
0"
b11000 4
12
01
1*
#1710000
0+
b10101011 8
0*
#1715000
b1 <
b101100000000000010110 :
b10110 =
02
11
1*
#1716000
0(
b1010010 5
#1720000
b10110 :
1(
b0 '
b0 9
b10101100 8
0*
#1725000
b10 <
1*
#1726000
0(
b1010011 5
#1730000
1(
b10101101 8
0*
#1735000
0%
1"
b10110 $
b10110 >
b0 <
1*
#1736000
0(
b1010100 5
#1740000
b101110000000000010110 :
1(
b10111 '
b10111 9
b10101110 8
0*
#1745000
b110100 7
b10110 ,
1.
01
1*
#1750000
b10101111 8
0*
#1755000
b110101 7
1*
#1760000
b10110000 8
0*
#1765000
b110110 7
1*
#1770000
b10110001 8
0*
#1775000
b110111 7
1*
#1780000
b10110010 8
0*
#1785000
b111000 7
1*
#1790000
b10110011 8
0*
#1795000
b111001 7
1*
#1800000
1+
b10110100 8
0*
#1805000
1%
b11001 ;
0"
b11001 4
0.
12
1*
#1810000
b10110101 8
0*
#1815000
b1 <
b101110000000000010111 :
b10111 =
02
11
1*
#1816000
0(
b1010101 5
#1820000
b10110110 8
0*
#1825000
01
1*
#1830000
b10111 :
1(
b0 '
b0 9
b10110111 8
0*
#1835000
b10 <
11
1*
#1836000
0(
b1010110 5
#1840000
1(
b10000000 '
b10000000 9
b10111000 8
0*
#1845000
0%
1"
b10111 $
b10111 >
b0 <
1*
#1846000
0(
b1010111 5
#1850000
b110000000000000010111 :
1(
b11000 '
b11000 9
b10111001 8
0*
#1855000
1%
b11010 ;
0"
b11010 4
12
01
1*
#1860000
b10111010 8
0*
#1865000
b1 <
b110000000000000011000 :
b11000 =
02
11
1*
#1866000
0(
b1011000 5
#1870000
b11000 :
1(
b0 '
b0 9
b10111011 8
0*
#1875000
b10 <
1*
#1876000
0(
b1011001 5
#1880000
1(
b10111100 8
0*
#1885000
0%
1"
b11000 $
b11000 >
b0 <
1*
#1886000
0(
b1011010 5
#1890000
b10111101 8
0*
#1895000
1%
b11011 ;
0"
b11011 4
12
01
1*
#1900000
b110010000000000011000 :
1(
b11001 '
b11001 9
0+
b10111110 8
0*
#1905000
b1 <
b110010000000000011001 :
b11001 =
02
11
1*
#1906000
0(
b1011011 5
#1910000
b11001 :
1(
b0 '
b0 9
b10111111 8
0*
#1915000
b10 <
1*
#1916000
0(
b1011100 5
#1920000
1(
b10000000 '
b10000000 9
b11000000 8
0*
#1925000
0%
1"
b11001 $
b11001 >
b0 <
1*
#1926000
0(
b1011101 5
#1930000
b110100000000000011001 :
1(
b11010 '
b11010 9
b11000001 8
0*
#1935000
b111010 7
b11001 ,
1.
01
1*
#1940000
b11000010 8
0*
#1945000
b111011 7
1*
#1950000
b11000011 8
0*
#1955000
b111100 7
1*
#1960000
b11000100 8
0*
#1965000
b111101 7
1*
#1970000
b11000101 8
0*
#1975000
b111110 7
1*
#1980000
b11000110 8
0*
#1985000
b111111 7
1*
#1990000
1+
b11000111 8
0*
#1995000
1%
b11100 ;
0"
b11100 4
0.
12
1*
#2000000
b11001000 8
0*
#2005000
b1 <
b110100000000000011010 :
b11010 =
02
11
1*
#2006000
0(
b1011110 5
#2010000
b11010 :
1(
b0 '
b0 9
b11001001 8
0*
#2015000
b10 <
1*
#2016000
0(
b1011111 5
#2020000
1(
b11001010 8
0*
#2025000
0%
1"
b11010 $
b11010 >
b0 <
1*
#2026000
0(
b1100000 5
#2030000
b11001011 8
0*
#2035000
1%
b11101 ;
0"
b11101 4
12
01
1*
#2040000
b110110000000000011010 :
1(
b11011 '
b11011 9
b11001100 8
0*
#2045000
b1 <
b110110000000000011011 :
b11011 =
02
11
1*
#2046000
0(
b1100001 5
#2050000
b11011 :
1(
b0 '
b0 9
b11001101 8
0*
#2055000
b10 <
1*
#2056000
0(
b1100010 5
#2060000
1(
b10000000 '
b10000000 9
b11001110 8
0*
#2065000
0%
1"
b11011 $
b11011 >
b0 <
1*
#2066000
0(
b1100011 5
#2070000
b111000000000000011011 :
1(
b11100 '
b11100 9
b11001111 8
0*
#2075000
1%
b11110 ;
0"
b11110 4
12
01
1*
#2080000
b11010000 8
0*
#2085000
b1 <
b111000000000000011100 :
b11100 =
02
11
1*
#2086000
0(
b1100100 5
#2090000
b11100 :
1(
b0 '
b0 9
0+
b11010001 8
0*
#2095000
b10 <
1*
#2096000
0(
b1100101 5
#2100000
b11010010 8
0*
#2105000
01
1*
#2110000
1(
b11010011 8
0*
#2115000
0%
1"
b11100 $
b11100 >
b0 <
11
1*
#2116000
0(
b1100110 5
#2120000
b111010000000000011100 :
1(
b11101 '
b11101 9
b11010100 8
0*
#2125000
b1000000 7
b11100 ,
1.
01
1*
#2130000
b11010101 8
0*
#2135000
b1000001 7
1*
#2140000
b11010110 8
0*
#2145000
b1000010 7
1*
#2150000
b11010111 8
0*
#2155000
b1000011 7
1*
#2160000
b11011000 8
0*
#2165000
b1000100 7
1*
#2170000
b11011001 8
0*
#2175000
b1000101 7
1*
#2180000
1+
b11011010 8
0*
#2185000
1%
b11111 ;
0"
b11111 4
0.
12
1*
#2190000
b11011011 8
0*
#2195000
b1 <
b111010000000000011101 :
b11101 =
02
11
1*
#2196000
0(
b1100111 5
#2200000
b11101 :
1(
b0 '
b0 9
b11011100 8
0*
#2205000
b10 <
1*
#2206000
0(
b1101000 5
#2210000
1(
b10000000 '
b10000000 9
b11011101 8
0*
#2215000
0%
1"
b11101 $
b11101 >
b0 <
1*
#2216000
0(
b1101001 5
#2220000
b111100000000000011101 :
1(
b11110 '
b11110 9
b11011110 8
0*
#2225000
1%
b100000 ;
0"
b100000 4
12
01
1*
#2230000
b11011111 8
0*
#2235000
b1 <
b111100000000000011110 :
b11110 =
02
11
1*
#2236000
0(
b1101010 5
#2240000
b11100000 8
0*
#2245000
01
1*
#2250000
b11110 :
1(
b0 '
b0 9
b11100001 8
0*
#2255000
b10 <
11
1*
#2256000
0(
b1101011 5
#2260000
1(
b11100010 8
0*
#2265000
0%
1"
b11110 $
b11110 >
b0 <
1*
#2266000
0(
b1101100 5
